flappy/Bird.py
flappy/FaceTracker.py
flappy/Flappy.py
flappy/GameEngine.py
flappy/LoadingBar.py
flappy/MusicPlayer.py
flappy/Pipes.py
flappy/Popup.py
flappy/Rules.py
flappy/UserForm.py
flappy/__init__.py
flappy/constants.py
flappy/credits.py
flappy/face_mesh.py
flappy/setup.py
flappy/util.py
flappy/audio/.DS_Store
flappy/audio/JurassicParkthemesong.wav
flappy/audio/crash.mp3
flappy/audio/flying.mp3
flappy/images/.DS_Store
flappy/images/GameOver.png
flappy/images/NHPS.png
flappy/images/Uphaar.png
flappy/images/bird.png
flappy/images/logo.png
flappy/images/pipe.png
flappy/images/pterodactyl.gif
flappy/images/pterodactyl.ico
flappy/images/pterodactyl.jpg
flappy/images/pterodactyl.png
flappy/mediapipe/modules/face_landmark/face_landmark_front_cpu.binarypb
flappy/res/JurassicPark.otf
flappy/res/leaderboard.xlsx
flappy_pterodactyl-1.0.3.dist-info/LICENSE
flappy_pterodactyl-1.0.3.dist-info/METADATA
flappy_pterodactyl-1.0.3.dist-info/WHEEL
flappy_pterodactyl-1.0.3.dist-info/entry_points.txt
flappy_pterodactyl-1.0.3.dist-info/top_level.txt
flappy_pterodactyl-1.0.3.dist-info/RECORD
