Metadata-Version: 2.1
Name: flappy-pterodactyl
Version: 1.0.3
Summary: A Flappy Pterodactyl game using AR and face tracking
Home-page: https://github.com/abhijitbhattacharjee/flappy
Author: Abhijit Bhattacharjee
Author-email: abhijit@example.com
License: MIT
Classifier: Programming Language :: Python :: 3
Classifier: License :: OSI Approved :: MIT License
Classifier: Operating System :: OS Independent
Requires-Python: >=3.6
License-File: LICENSE
Requires-Dist: pygame
Requires-Dist: mediapipe
Requires-Dist: pyglet
Requires-Dist: screeninfo
Requires-Dist: opencv-python
Requires-Dist: openpyxl
Requires-Dist: pandas
Requires-Dist: pillow
Requires-Dist: pyaudio
Requires-Dist: playsound
